<?xml version='1.0' encoding='UTF-8'?>
<!DOCTYPE beans PUBLIC '-//SPRING//DTD BEAN//EN' 'http://www.springframework.org/dtd/spring-beans.dtd'>

<beans>

    <!--  Capability Conditions -->

    <bean id="capabilityCondition.base"
          abstract="true">
        <property name="permissionService" ref="permissionService" /> <!--  use lower case service to enhance performance -->
        <property name="nodeService" ref="nodeService" />             <!--  use lower case service to enhance performance -->
        <property name="freezeService" ref="FreezeService" />
        <property name="recordService" ref="RecordService" />
        <property name="filePlanService" ref="FilePlanService" />
        <property name="dispositionService" ref="DispositionService" />
        <property name="recordFolderService" ref="recordFolderService" />
        <property name="transactionalResourceHelper" ref="rm.transactionalResourceHelper" />
    </bean>

    <bean id="capabilityCondition.frozen"
          parent="capabilityCondition.base"
          class="org.alfresco.module.org_alfresco_module_rm.capability.declarative.condition.FrozenCapabilityCondition">
       <property name="holdService" ref="HoldService" />
    </bean>

    <bean id="capabilityCondition.frozenOrFrozenChildren"
          parent="capabilityCondition.base"
          class="org.alfresco.module.org_alfresco_module_rm.capability.declarative.condition.FrozenCapabilityCondition">
    	<property name="checkChildren" value="true" />
       <property name="holdService" ref="HoldService" />
    </bean>

    <bean id="capabilityCondition.frozenOrHold"
          parent="capabilityCondition.base"
          class="org.alfresco.module.org_alfresco_module_rm.capability.declarative.condition.FrozenOrHoldCondition">
    </bean>

    <bean id="capabilityCondition.cutoff"
          parent="capabilityCondition.base"
          class="org.alfresco.module.org_alfresco_module_rm.capability.declarative.condition.CutoffCapabilityCondition">
    </bean>

    <bean id="capabilityCondition.closed"
          parent="capabilityCondition.base"
          class="org.alfresco.module.org_alfresco_module_rm.capability.declarative.condition.ClosedCapabilityCondition">
    </bean>

    <bean id="capabilityCondition.declared"
          parent="capabilityCondition.base"
          class="org.alfresco.module.org_alfresco_module_rm.capability.declarative.condition.DeclaredCapabilityCondition">
    </bean>

    <bean id="capabilityCondition.filling"
          parent="capabilityCondition.base"
          class="org.alfresco.module.org_alfresco_module_rm.capability.declarative.condition.FillingCapabilityCondition">
    </bean>

    <bean id="capabilityCondition.transferred"
          parent="capabilityCondition.base"
          class="org.alfresco.module.org_alfresco_module_rm.capability.declarative.condition.TransferredCapabilityCondition">
    </bean>

    <bean id="capabilityCondition.destroyed"
          parent="capabilityCondition.base"
          class="org.alfresco.module.org_alfresco_module_rm.capability.declarative.condition.DestroyedCapabilityCondition">
    </bean>

    <bean id="capabilityCondition.vitalRecordOrFolder"
          parent="capabilityCondition.base"
          class="org.alfresco.module.org_alfresco_module_rm.capability.declarative.condition.VitalRecordOrFolderCapabilityCondition">
    </bean>

    <bean id="capabilityCondition.recordFiled"
          parent="capabilityCondition.base"
          class="org.alfresco.module.org_alfresco_module_rm.capability.declarative.condition.RecordFiledCapabilityCondition">
    </bean>

    <bean id="capabilityCondition.destroyMayBeScheduled"
          parent="capabilityCondition.base"
          class="org.alfresco.module.org_alfresco_module_rm.capability.declarative.condition.MayBeScheduledCapabilityCondition">
    	<property name="dispositionService" ref="DispositionService"/>
    	<property name="dispositionAction"  value="destroy"/>
    </bean>

    <bean id="capabilityCondition.destroyIsScheduled"
          parent="capabilityCondition.base"
          class="org.alfresco.module.org_alfresco_module_rm.capability.declarative.condition.IsScheduledCapabilityCondition">
    	<property name="dispositionService" ref="DispositionService"/>
    	<property name="dispositionAction"  value="destroy"/>
    </bean>

    <bean id="capabilityCondition.destroyIsScheduledOrComplete"
          parent="capabilityCondition.base"
          class="org.alfresco.module.org_alfresco_module_rm.capability.declarative.condition.AtLeastOneCondition">
    	<property name="conditions">
    		<list>
    			<ref bean="capabilityCondition.destroyed" />
    			<ref bean="capabilityCondition.destroyIsScheduled" />
    		</list>
    	</property>
    </bean>

    <bean id="capabilityCondition.hasEvents"
          parent="capabilityCondition.base"
          class="org.alfresco.module.org_alfresco_module_rm.capability.declarative.condition.HasEventsCapabilityCondition">
    	<property name="dispositionService" ref="DispositionService"/>
    </bean>

    <bean id="capabilityCondition.fileable"
          parent="capabilityCondition.base"
          class="org.alfresco.module.org_alfresco_module_rm.capability.declarative.condition.FileableCapabilityCondition">
    	<property name="dictionaryService" ref="DictionaryService"/>
    </bean>

    <bean id="capabilityCondition.transferIsScheduled"
          parent="capabilityCondition.base"
          class="org.alfresco.module.org_alfresco_module_rm.capability.declarative.condition.IsScheduledCapabilityCondition">
    	<property name="dispositionService" ref="DispositionService"/>
    	<property name="dispositionAction" value="transfer"/>
    </bean>

    <bean id="capabilityCondition.accessionIsScheduled"
          parent="capabilityCondition.base"
          class="org.alfresco.module.org_alfresco_module_rm.capability.declarative.condition.IsScheduledCapabilityCondition">
    	<property name="dispositionService" ref="DispositionService"/>
    	<property name="dispositionAction" value="accession"/>
    </bean>

    <bean id="capabilityCondition.cutoffIsScheduled"
          parent="capabilityCondition.base"
          class="org.alfresco.module.org_alfresco_module_rm.capability.declarative.condition.IsScheduledCapabilityCondition">
    	<property name="dispositionService" ref="DispositionService"/>
    	<property name="dispositionAction" value="cutoff"/>
    </bean>

    <bean id="capabilityCondition.retentionIsScheduled"
          parent="capabilityCondition.base"
          class="org.alfresco.module.org_alfresco_module_rm.capability.declarative.condition.IsScheduledCapabilityCondition">
    	<property name="dispositionService" ref="DispositionService"/>
    	<property name="dispositionAction" value="retain"/>
    </bean>

    <bean id="capabilityCondition.isTransferAccession"
          parent="capabilityCondition.base"
          class="org.alfresco.module.org_alfresco_module_rm.capability.declarative.condition.IsTransferAccessionCapabilityCondition">
    </bean>

    <bean id="capabilityCondition.isTransferring"
          parent="capabilityCondition.base"
          class="org.alfresco.module.org_alfresco_module_rm.capability.declarative.condition.HasAspectCapabilityCondition">
       <property name="aspectName" value="rma:transferring"/>
       <property name="namespaceService" ref="NamespaceService"/>
    </bean>

    <bean id="capabilityCondition.hasDispositionAsOfDate"
          parent="capabilityCondition.base"
          class="org.alfresco.module.org_alfresco_module_rm.capability.declarative.condition.HasDispositionDateCapabilityCondition">
       <property name="dispositionService" ref="DispositionService"/>
    </bean>

    <bean id="capabilityCondition.lastDispositionActionCutoff"
          parent="capabilityCondition.base"
          class="org.alfresco.module.org_alfresco_module_rm.capability.declarative.condition.LastDispositionActionCondition">
       <property name="dispositionService" ref="DispositionService"/>
       <property name="dispositionActionName" value="cutoff"/>
    </bean>

   <bean id="capabilityCondition.isRecord"
         parent="capabilityCondition.base"
         class="org.alfresco.module.org_alfresco_module_rm.capability.declarative.condition.IsRecordCondition">
   </bean>

   <bean id="capabilityCondition.isRecordFolder"
         parent="capabilityCondition.base"
         class="org.alfresco.module.org_alfresco_module_rm.capability.declarative.condition.IsRecordFolderCondition">
   </bean>

   <bean id="capabilityCondition.isRecordCategory"
         parent="capabilityCondition.base"
         class="org.alfresco.module.org_alfresco_module_rm.capability.declarative.condition.IsRecordCategoryCondition">
   </bean>

   <bean id="capabilityCondition.isRejectedRecord"
          parent="capabilityCondition.base"
          class="org.alfresco.module.org_alfresco_module_rm.capability.declarative.condition.HasAspectCapabilityCondition">
       <property name="aspectName" value="rma:recordRejectionDetails"/>
       <property name="namespaceService" ref="NamespaceService"/>
   </bean>

   <bean id="capabilityCondition.isClassified"
          parent="capabilityCondition.base"
          class="org.alfresco.module.org_alfresco_module_rm.capability.declarative.condition.IsClassifiedCapabilityCondition">
    	<property name="dispositionService" ref="DispositionService"/>
   </bean>

   <bean id="capabilityCondition.fail"
         parent="capabilityCondition.base"
         class="org.alfresco.module.org_alfresco_module_rm.capability.declarative.condition.FailCapabilityCondition">
   </bean>

   <bean id="capabilityCondition.isRecordOriginatingLocationSet"
         parent="capabilityCondition.base"
         class="org.alfresco.module.org_alfresco_module_rm.capability.declarative.condition.IsPropertySetCondition">
      <property name="propertyName" value="rma:recordOriginatingLocation"/>
      <property name="namespaceService" ref="NamespaceService" />
   </bean>

   <bean id="capabilityCondition.hasFillingOnHolds"
         parent="capabilityCondition.base"
         class="org.alfresco.module.org_alfresco_module_rm.capability.declarative.condition.HoldCapabilityCondition">
      <property name="includedInHold" value="false"/>
      <property name="holdService" ref="HoldService" />
   </bean>

   <bean id="capabilityCondition.hasFillingOnHeld"
         parent="capabilityCondition.base"
         class="org.alfresco.module.org_alfresco_module_rm.capability.declarative.condition.HoldCapabilityCondition">
      <property name="includedInHold" value="true"/>
      <property name="holdService" ref="HoldService" />
   </bean>
   
   <bean id="capabilityCondition.hasFillingOnHoldContainer"
         parent="capabilityCondition.base"
         class="org.alfresco.module.org_alfresco_module_rm.capability.declarative.condition.FillingOnHoldContainerCapabilityCondition">
   </bean>

</beans>